arclength_continuation/__init__.py
arclength_continuation/__main__.py
arclength_continuation/args.py
arclength_continuation/continuation.py
arclength_continuation/parameters.py
arclength_continuation-0.1.7.dist-info/licenses/LICENSE
arclength_continuation-0.1.7.dist-info/METADATA
arclength_continuation-0.1.7.dist-info/WHEEL
arclength_continuation-0.1.7.dist-info/entry_points.txt
arclength_continuation-0.1.7.dist-info/top_level.txt
arclength_continuation-0.1.7.dist-info/RECORD
