Metadata-Version: 2.4
Name: arclength_continuation
Version: 0.1.7
Summary: Python script that demonstrates how to use pseudo-arclength continuation.
Author-email: Raymond Langer <raymond.langer@gmx.net>
License-Expression: MIT
Project-URL: homepage, https://github.com/raymondlanger/arclength_continuation
Keywords: math,continuation,numerical methods
Classifier: Development Status :: 3 - Alpha
Classifier: Intended Audience :: Science/Research
Classifier: Operating System :: POSIX :: Linux
Classifier: Programming Language :: Python :: 3
Classifier: Programming Language :: Python :: 3.7
Classifier: Programming Language :: Python :: 3.8
Classifier: Programming Language :: Python :: 3.9
Classifier: Programming Language :: Python :: 3.10
Classifier: Programming Language :: Python :: 3.11
Classifier: Programming Language :: Python :: 3.12
Classifier: Programming Language :: Python :: 3.13
Requires-Python: >=3.7
License-File: LICENSE
Requires-Dist: numpy>=1.21
Requires-Dist: matplotlib>=3.4
Dynamic: license-file
